Metadata-Version: 2.4
Name: da-mcp-server
Version: 1.0.1
Summary: 晨舟财务会计软件 MCP (Model Context Protocol) 服务器
Home-page: https://gitee.com/jlmpp/da_mcp_server
Author: DeepSea Accounting Team
Author-email: jianglinming@gmail.com
License: MIT
Classifier: Development Status :: 4 - Beta
Classifier: Intended Audience :: Developers
Classifier: License :: OSI Approved :: MIT License
Classifier: Operating System :: OS Independent
Classifier: Programming Language :: Python :: 3
Classifier: Programming Language :: Python :: 3.8
Classifier: Programming Language :: Python :: 3.9
Classifier: Programming Language :: Python :: 3.10
Classifier: Programming Language :: Python :: 3.11
Classifier: Programming Language :: Python :: 3.12
Classifier: Topic :: Office/Business :: Financial :: Accounting
Classifier: Topic :: Software Development :: Libraries :: Python Modules
Requires-Python: >=3.8
License-File: LICENSE
Requires-Dist: fastmcp==2.13.0.2
Requires-Dist: pydantic==2.12.4
Requires-Dist: requests==2.32.5
Requires-Dist: diskcache==5.6.3
Requires-Dist: cachetools==6.2.1
Requires-Dist: exceptiongroup==1.3.0
Requires-Dist: pathvalidate==3.3.1
Provides-Extra: dev
Requires-Dist: pyinstaller==6.16.0; extra == "dev"
Requires-Dist: build>=0.8.0; extra == "dev"
Requires-Dist: twine>=4.0.0; extra == "dev"
Requires-Dist: pytest>=7.0.0; extra == "dev"
Requires-Dist: pytest-cov>=4.0.0; extra == "dev"
Requires-Dist: black>=22.0.0; extra == "dev"
Requires-Dist: flake8>=5.0.0; extra == "dev"
Requires-Dist: mypy>=1.0.0; extra == "dev"
Dynamic: author
Dynamic: author-email
Dynamic: classifier
Dynamic: description
Dynamic: description-content-type
Dynamic: home-page
Dynamic: license
Dynamic: license-file
Dynamic: provides-extra
Dynamic: requires-dist
Dynamic: requires-python
Dynamic: summary
